byot/__init__.py
byot/assertions.py
byot/features.py
byot/filters.py
byot/fixtures.py
byot/loaders.py
byot/matchers.py
byot/results.py
byot/runners.py
byot/scenarii.py
byot/styles.py
byot/suites.py
byot/walkers.py
byot/tests/__init__.py
byot/tests/test_assertions.py
byot/tests/test_features.py
byot/tests/test_filters.py
byot/tests/test_fixtures.py
byot/tests/test_loaders.py
byot/tests/test_matchers.py
byot/tests/test_results.py
byot/tests/test_runners.py
byot/tests/test_scenarii.py
byot/tests/test_styles.py
byot/tests/test_suites.py
byot/tests/test_walkers.py
byot-2.0.1.data/scripts/byot-run
byot-2.0.1.dist-info/DESCRIPTION.rst
byot-2.0.1.dist-info/METADATA
byot-2.0.1.dist-info/RECORD
byot-2.0.1.dist-info/WHEEL
byot-2.0.1.dist-info/metadata.json
byot-2.0.1.dist-info/top_level.txt
