Metadata-Version: 2.0
Name: byot
Version: 2.0.1
Summary: Build Your Own Tests.
Home-page: https://launchpad.net/byot
Author: Vincent Ladeuil
Author-email: v.ladeuil+lp@free.fr
License: GPLv3
Platform: UNKNOWN
Requires-Dist: pep8
Requires-Dist: python-subunit
Requires-Dist: testtools
